tigramite/__init__.py
tigramite/causal_effects.py
tigramite/causal_mediation.py
tigramite/data_processing.py
tigramite/graphs.py
tigramite/jpcmciplus.py
tigramite/lpcmci.py
tigramite/models.py
tigramite/pcmci.py
tigramite/pcmci_base.py
tigramite/plotting.py
tigramite/rpcmci.py
tigramite/independence_tests/LBFGS.py
tigramite/independence_tests/__init__.py
tigramite/independence_tests/cmiknn.py
tigramite/independence_tests/cmiknn_mixed.py
tigramite/independence_tests/cmisymb.py
tigramite/independence_tests/gpdc.py
tigramite/independence_tests/gpdc_torch.py
tigramite/independence_tests/gsquared.py
tigramite/independence_tests/independence_tests_base.py
tigramite/independence_tests/oracle_conditional_independence.py
tigramite/independence_tests/pairwise_CI.py
tigramite/independence_tests/parcorr.py
tigramite/independence_tests/parcorr_mult.py
tigramite/independence_tests/parcorr_wls.py
tigramite/independence_tests/regressionCI.py
tigramite/independence_tests/robust_parcorr.py
tigramite/toymodels/__init__.py
tigramite/toymodels/context_model.py
tigramite/toymodels/non_additive.py
tigramite/toymodels/structural_causal_processes.py
tigramite/toymodels/surrogate_generator.py
tigramite-5.2.9.7.dist-info/METADATA
tigramite-5.2.9.7.dist-info/WHEEL
tigramite-5.2.9.7.dist-info/top_level.txt
tigramite-5.2.9.7.dist-info/RECORD
